asyncr/__init__.py
asyncr-0.1.0.dist-info/METADATA
asyncr-0.1.0.dist-info/WHEEL
asyncr-0.1.0.dist-info/licenses/LICENSE
asyncr-0.1.0.dist-info/RECORD
